README.md
setup.py
calaccess_crawler/__init__.py
calaccess_crawler/items.py
calaccess_crawler/loaders.py
calaccess_crawler/middlewares.py
calaccess_crawler/pipelines.py
calaccess_crawler/proxies.py
calaccess_crawler/settings.py
calaccess_crawler/spiders/__init__.py
calaccess_crawler/spiders/candidates_spider.py
calaccess_crawler/spiders/incumbents_spider.py
calaccess_crawler/spiders/propositions_spider.py
scrapy_calaccess_crawler.egg-info/PKG-INFO
scrapy_calaccess_crawler.egg-info/SOURCES.txt
scrapy_calaccess_crawler.egg-info/dependency_links.txt
scrapy_calaccess_crawler.egg-info/requires.txt
scrapy_calaccess_crawler.egg-info/top_level.txt